[
  {
    "name": "Võ Ty",
    "uid": "100037820580122",
    "time": "17:32:25 - 26/11/2024",
    "reason": "Đã tự động rời khỏi nhóm.",
    "facebook": "https://www.facebook.com/100037820580122"
  },
  {
    "name": "Văn Thuận",
    "uid": "100082753143406",
    "time": "22:03:27 - 26/11/2024",
    "reason": "Đã tự động rời khỏi nhóm.",
    "facebook": "https://www.facebook.com/100082753143406"
  },
  {
    "name": "Nguyễn Thuỳ Trang",
    "uid": "100080418210790",
    "time": "08:27:44 - 27/11/2024",
    "reason": "Đã tự động rời khỏi nhóm.",
    "facebook": "https://www.facebook.com/100080418210790"
  },
  {
    "name": "Đình Hùngg",
    "uid": "100080328352421",
    "time": "08:53:25 - 27/11/2024",
    "reason": "Đã tự động rời khỏi nhóm.",
    "facebook": "https://www.facebook.com/100080328352421"
  },
  {
    "name": "Kieu Anh Ng",
    "uid": "100074824285996",
    "time": "09:41:16 - 27/11/2024",
    "reason": "Đã tự động rời khỏi nhóm.",
    "facebook": "https://www.facebook.com/100074824285996"
  },
  {
    "name": "Thành Nam",
    "uid": "100030938172857",
    "time": "10:08:51 - 27/11/2024",
    "reason": "Đã tự động rời khỏi nhóm.",
    "facebook": "https://www.facebook.com/100030938172857"
  },
  {
    "name": "Huỳnh Bảo",
    "uid": "100028237654064",
    "time": "10:20:11 - 27/11/2024",
    "reason": "Đã tự động rời khỏi nhóm.",
    "facebook": "https://www.facebook.com/100028237654064"
  },
  {
    "name": "Người dùng facebook",
    "uid": "100089429390870",
    "time": "12:27:21 - 27/11/2024",
    "reason": "Đã tự động rời khỏi nhóm.",
    "facebook": "https://www.facebook.com/100089429390870"
  },
  {
    "name": "Người dùng facebook",
    "uid": "100064997152842",
    "time": "15:34:13 - 27/11/2024",
    "reason": "Đã tự động rời khỏi nhóm.",
    "facebook": "https://www.facebook.com/100064997152842"
  }
]